examples/__init__.py
examples/gpmp_example01_materncov.py
examples/gpmp_example02_1d_interpolation.py
examples/gpmp_example02_1d_interpolation_peaks.py
examples/gpmp_example03_2d.py
examples/gpmp_example04_nd.py
examples/gpmp_example05_1d_custom_kernel.py
examples/gpmp_example06_1d_regression.py
examples/gpmp_example10_sample_paths.py
examples/gpmp_example11_sample_paths_noisy_obs.py
examples/gpmp_example20_1d_interpolation_variation_remap.py
examples/gpmp_example21_1d_interpolation_variation_reml.py
examples/gpmp_example22_1d_interpolation_variation_ml.py
examples/gpmp_example30_scoringrules.py
gpmp/__init__.py
gpmp/core.py
gpmp/kernel.py
gpmp/num.py
gpmp/misc/__init__.py
gpmp/misc/calibration.py
gpmp/misc/dataframe.py
gpmp/misc/designs.py
gpmp/misc/modeldiagnosis.py
gpmp/misc/plotutils.py
gpmp/misc/scoringrules.py
gpmp/misc/testfunctions.py
tests/__init__.py
tests/test_examples.py
tests/test_jax.py
tests/test_scoringrules.py
gpmp-0.9.18.dist-info/AUTHORS.md
gpmp-0.9.18.dist-info/LICENSE.txt
gpmp-0.9.18.dist-info/METADATA
gpmp-0.9.18.dist-info/WHEEL
gpmp-0.9.18.dist-info/top_level.txt
gpmp-0.9.18.dist-info/RECORD
