Metadata-Version: 2.1
Name: gpmp
Version: 0.9.18
Summary: GPmp: the Gaussian process micro package
Author-email: Emmanuel Vazquez <emmanuel.vazquez@centralesupelec.fr>
License: GNU GENERAL PUBLIC LICENSE
Project-URL: Homepage, https://github.com/gpmp-dev/gpmp
Keywords: Gaussian processes,kriging
Classifier: Programming Language :: Python :: 3
Classifier: License :: OSI Approved :: GNU General Public License v3 or later (GPLv3+)
Classifier: Operating System :: OS Independent
Requires-Python: >=3.6
License-File: LICENSE.txt
License-File: AUTHORS.md
Requires-Dist: numpy<2
Requires-Dist: scipy>=1.8.0
Requires-Dist: matplotlib
Provides-Extra: dev
